{
	"name": "Tyopaikka_proj_nopea",
	"properties": {
		"linkedServiceName": {
			"referenceName": "AzureSqlDatabase1",
			"type": "LinkedServiceReference"
		},
		"annotations": [],
		"type": "AzureSqlTable",
		"schema": [
			{
				"name": "Toimiala",
				"type": "varchar"
			},
			{
				"name": "Tol",
				"type": "int",
				"precision": 10
			},
			{
				"name": "Tyyppi",
				"type": "varchar"
			},
			{
				"name": "Vuosi",
				"type": "int",
				"precision": 10
			},
			{
				"name": "Alue",
				"type": "varchar"
			},
			{
				"name": "Arvo",
				"type": "int",
				"precision": 10
			},
			{
				"name": "ArvoP",
				"type": "decimal",
				"precision": 5,
				"scale": 2
			}
		],
		"typeProperties": {
			"schema": "dbo",
			"table": "Tyopaikka_proj_nopea"
		}
	}
}